langchain_gradientai_narsi/__init__.py
langchain_gradientai_narsi/chat_models.py
langchain_gradientai_narsi/constants.py
langchain_gradientai_narsi-0.1.3.dist-info/LICENSE
langchain_gradientai_narsi-0.1.3.dist-info/METADATA
langchain_gradientai_narsi-0.1.3.dist-info/WHEEL
langchain_gradientai_narsi-0.1.3.dist-info/RECORD
