Metadata-Version: 2.3
Name: langchain-gradientai-narsi
Version: 0.1.3
Summary: An integration package connecting Digitalocean and LangChain
License: MIT
Requires-Python: >=3.9,<4.0
Classifier: License :: OSI Approved :: MIT License
Classifier: Programming Language :: Python :: 3
Classifier: Programming Language :: Python :: 3.9
Classifier: Programming Language :: Python :: 3.10
Classifier: Programming Language :: Python :: 3.11
Classifier: Programming Language :: Python :: 3.12
Classifier: Programming Language :: Python :: 3.13
Requires-Dist: do-gradientai (>=0.1.0a19,<0.2.0)
Requires-Dist: langchain-core (>=0.3.15,<0.4.0)
Requires-Dist: langchain-tests (>=0.3.20,<0.4.0)
Requires-Dist: python-digitalocean (>=1.17.0,<2.0.0)
Requires-Dist: python-dotenv (>=1.1.1,<2.0.0)
Requires-Dist: typing_extensions (>=4.0.0,<5.0.0)
Project-URL: Repository, https://github.com/bnarasimha21/langchain-gradientai-narsi
Project-URL: Release Notes, https://github.com/langchain-ai/langchain/releases?q=tag%3A%22gradientai%3D%3D0%22&expanded=true
Project-URL: Source Code, https://github.com/langchain-ai/langchain/tree/master/libs/partners/gradientai
